.mina/red.toml
avilla/red/__init__.py
avilla/red/account.py
avilla/red/capability.py
avilla/red/collector/__init__.py
avilla/red/collector/connection.py
avilla/red/exception.py
avilla/red/net/__init__.py
avilla/red/net/base.py
avilla/red/net/ws_client.py
avilla/red/perform/__init__.py
avilla/red/perform/action/__init__.py
avilla/red/perform/action/friend.py
avilla/red/perform/action/group.py
avilla/red/perform/action/member.py
avilla/red/perform/action/message.py
avilla/red/perform/context.py
avilla/red/perform/event/__init__.py
avilla/red/perform/event/group.py
avilla/red/perform/event/lifespan.py
avilla/red/perform/event/member.py
avilla/red/perform/event/message.py
avilla/red/perform/event/relationship.py
avilla/red/perform/message/deserialize.py
avilla/red/perform/message/serialize.py
avilla/red/perform/query.py
avilla/red/perform/resource_fetch.py
avilla/red/protocol.py
avilla/red/resource.py
avilla/red/service.py
avilla/red/utils.py
avilla_red-1.0.0a26.dist-info/METADATA
avilla_red-1.0.0a26.dist-info/WHEEL
avilla_red-1.0.0a26.dist-info/licenses/LICENSE
avilla_red-1.0.0a26.dist-info/RECORD
